owl_eye/__init__.py
owl_eye/banner.py
owl_eye/main.py
owl_eye/utils.py
owl_eye/whois_lookup.py
owl_eye-0.1.6.dist-info/METADATA
owl_eye-0.1.6.dist-info/WHEEL
owl_eye-0.1.6.dist-info/entry_points.txt
owl_eye-0.1.6.dist-info/top_level.txt
owl_eye-0.1.6.dist-info/RECORD
