Metadata-Version: 2.2
Name: owl-eye
Version: 0.1.6
Summary: A WHOIS lookup tool
Home-page: https://github.com/ishanoshada/Owl-Eye
Author: Ishan Oshada
Classifier: Programming Language :: Python :: 3
Classifier: License :: OSI Approved :: MIT License
Classifier: Operating System :: OS Independent
Requires-Dist: colorama
Requires-Dist: pyfiglet
Requires-Dist: requests
Requires-Dist: beautifulsoup4
Dynamic: author
Dynamic: classifier
Dynamic: description
Dynamic: description-content-type
Dynamic: home-page
Dynamic: requires-dist
Dynamic: summary
